{
  "size": {
    "border": {
      "input-focus": {
        "value": "{size.20}",
        "type": "sizing"
      },
      "input-checked": {
        "value": "{size.20}",
        "type": "sizing"
      },
      "input": {
        "value": "{size.12}",
        "type": "sizing"
      },
      "focus-ring": {
        "value": "{size.50}",
        "type": "sizing"
      },
      "error-ring": {
        "value": "{size.12}",
        "type": "sizing"
      },
      "error-ring-offset": {
        "value": "{size.20}",
        "type": "sizing"
      }
    }
  },
  "border": {
    "radius": {
      "input": {
        "value": "{border.radius.150}",
        "type": "borderRadius"
      },
      "input-full": {
        "value": "{border.radius.full}",
        "type": "borderRadius"
      }
    }
  }
}